workflowy_assistant.py
workflowy_assistant-0.0.5.dist-info/LICENSE.txt
workflowy_assistant-0.0.5.dist-info/METADATA
workflowy_assistant-0.0.5.dist-info/WHEEL
workflowy_assistant-0.0.5.dist-info/top_level.txt
workflowy_assistant-0.0.5.dist-info/RECORD
